MANIFEST.in
README.md
requirements.txt
setup.py
cloud_sdk.egg-info/PKG-INFO
cloud_sdk.egg-info/SOURCES.txt
cloud_sdk.egg-info/dependency_links.txt
cloud_sdk.egg-info/requires.txt
cloud_sdk.egg-info/top_level.txt
cloudsdk/__init__.py
cloudsdk/config.py
cloudsdk/api/__init__.py
cloudsdk/api/api_cloud.py
cloudsdk/api/drivers/__init__.py
cloudsdk/api/drivers/http_client_driver.py
cloudsdk/api/drivers/qingcloud/__init__.py
cloudsdk/api/drivers/qingcloud/api_request.py
cloudsdk/api/drivers/qingcloud/http_client.py
cloudsdk/models/__init__.py
cloudsdk/models/bots_model.py
cloudsdk/models/cache_model.py
cloudsdk/models/eip_model.py
cloudsdk/models/hadoop_model.py
cloudsdk/models/instance_model.py
cloudsdk/models/job_model.py
cloudsdk/models/kafka_model.py
cloudsdk/models/loadbalancer_model.py
cloudsdk/models/mongos_model.py
cloudsdk/models/quota_model.py
cloudsdk/models/rdb_model.py
cloudsdk/models/router_model.py
cloudsdk/models/s2_model.py
cloudsdk/models/snapshots_model.py
cloudsdk/models/spark_model.py
cloudsdk/models/user_model.py
cloudsdk/models/volume_model.py
cloudsdk/models/vxnet_model.py
cloudsdk/models/zone_model.py
cloudsdk/models/zookeeper_model.py