Metadata-Version: 1.0
Name: cloud-sdk
Version: 0.1.2
Summary: 该库主要是封装了cloud Iaas的API，进行方便获取与操作IaaS资源
Home-page: https://github.com/xhuaustc/cloud-sdk.git
Author: xhua
Author-email: pxhua@aliyun.com
License: UNKNOWN
Keywords: Qingcloud,Iaas
Platform: UNKNOWN
